{
    "So cong thuc khong dau tu": 283,
    "ASP": 340,
    "DBT": 209,
    "LM8": 181,
    "PAN": 174,
    "PET": 168,
    "NO1": 143,
    "SMC": 143,
    "NAF": 124,
    "APH": 105,
    "KDH": 91,
    "FCM": 84,
    "PSH": 83,
    "GTA": 78,
    "TNA": 76,
    "SVC": 76,
    "CTD": 73,
    "PMG": 67,
    "PNC": 63,
    "ADS": 55,
    "DLG": 53,
    "MHC": 52,
    "TDG": 52,
    "DAG": 50,
    "VID": 40,
    "SRF": 39,
    "HTV": 39,
    "ASM": 38,
    "PLP": 37,
    "TNI": 34,
    "NHH": 34,
    "VIP": 33,
    "GIL": 32,
    "VDP": 30,
    "HHS": 27,
    "DTA": 26,
    "HT1": 26,
    "KHP": 25,
    "DBC": 25,
    "TDC": 23,
    "BCG": 23,
    "GEX": 23,
    "SC5": 23,
    "HAX": 22,
    "TSC": 22,
    "TIX": 21,
    "TVT": 21,
    "C32": 20,
    "CCI": 19,
    "TN1": 19,
    "BBC": 19,
    "HAR": 18,
    "DXS": 17,
    "TNT": 16,
    "HVX": 15,
    "VPH": 14,
    "PGC": 14,
    "FIT": 14,
    "CMV": 14,
    "RDP": 13,
    "DGC": 13,
    "PVP": 13,
    "LGL": 13,
    "SAM": 12,
    "PTB": 12,
    "PTC": 12,
    "TDW": 12,
    "VCG": 11,
    "HAS": 11,
    "ADG": 11,
    "MCG": 11,
    "HII": 11,
    "TRC": 10,
    "PIT": 10,
    "DXV": 9,
    "HU1": 9,
    "MWG": 9,
    "ABR": 9,
    "LHG": 8,
    "TPC": 8,
    "SHI": 8,
    "DAH": 7,
    "HUB": 7,
    "SCD": 7,
    "TMT": 7,
    "PLX": 7,
    "VAF": 7,
    "CII": 7,
    "PHR": 6,
    "GEG": 6,
    "SZL": 6,
    "TLH": 6,
    "AAT": 6,
    "FRT": 6,
    "AAA": 6,
    "VIC": 6,
    "DHM": 5,
    "NSC": 5,
    "D2D": 5,
    "AAM": 5,
    "DAT": 5,
    "SFG": 5,
    "VFG": 5,
    "VMD": 5,
    "VNE": 5,
    "DHA": 5,
    "YBM": 5,
    "UDC": 5,
    "YEG": 5,
    "IDI": 5,
    "DXG": 4,
    "VOS": 4,
    "HAP": 4,
    "ASG": 4,
    "TTF": 4,
    "DGW": 4,
    "KHG": 4,
    "CTI": 4,
    "SAV": 4,
    "PGV": 4,
    "DPM": 4,
    "LEC": 3,
    "SVI": 3,
    "CLW": 3,
    "VTB": 3,
    "QBS": 3,
    "PHC": 3,
    "SVT": 3,
    "TCR": 3,
    "SHA": 3,
    "BKG": 3,
    "APC": 3,
    "HNG": 3,
    "PJT": 3,
    "HVH": 3,
    "TRA": 3,
    "HTL": 3,
    "ITC": 3,
    "GVR": 3,
    "TDH": 3,
    "NLG": 3,
    "COM": 2,
    "GMC": 2,
    "SMA": 2,
    "HTI": 2,
    "PC1": 2,
    "PTL": 2,
    "NHT": 2,
    "KSB": 2,
    "SCR": 2,
    "CIG": 2,
    "QCG": 2,
    "KBC": 2,
    "BFC": 2,
    "ITA": 2,
    "LSS": 1,
    "TYA": 1,
    "PVT": 1,
    "GSP": 1,
    "HCD": 1,
    "DRH": 1,
    "SFC": 1,
    "SBV": 1,
    "MSN": 1,
    "VNG": 1,
    "SZC": 1,
    "THG": 1,
    "CCL": 1,
    "SJS": 1,
    "BHN": 1,
    "HMC": 1,
    "FDC": 1,
    "VPG": 1,
    "VRC": 1,
    "VNS": 1,
    "HPG": 1,
    "NBB": 1,
    "HAG": 1,
    "HHV": 1,
    "BTT": 1,
    "SGT": 1,
    "SFI": 1,
    "THI": 1,
    "BTP": 1,
    "HU3": 1,
    "ST8": 1,
    "HAH": 1,
    "CSV": 1,
    "AGG": 1,
    "BAF": 1,
    "HDC": 1,
    "IMP": 1,
    "TEG": 1,
    "VSC": 1,
    "LCG": 1,
    "VHC": 1,
    "VNM": 1,
    "FPT": 1
}