{
    "IDI": 1702,
    "PTL": 519,
    "FCM": 460,
    "MWG": 435,
    "DHM": 370,
    "TDC": 282,
    "BGM": 275,
    "ASP": 270,
    "CLG": 249,
    "PET": 227,
    "HAX": 216,
    "TIE": 213,
    "CDO": 203,
    "MHC": 175,
    "HVG": 168,
    "PTC": 161,
    "NotInvest": 157,
    "HAG": 154,
    "VNA": 150,
    "DIC": 136,
    "POM": 136,
    "LCG": 133,
    "UDC": 124,
    "SHI": 106,
    "DTA": 95,
    "VMD": 92,
    "CMX": 91,
    "L10": 91,
    "VOS": 90,
    "LCM": 88,
    "TLH": 80,
    "FIT": 78,
    "LM8": 78,
    "VCF": 69,
    "HAR": 68,
    "TTF": 64,
    "NVT": 62,
    "BFC": 58,
    "TSC": 56,
    "DLG": 56,
    "CMG": 52,
    "VHG": 50,
    "VNG": 44,
    "KSB": 44,
    "PIT": 43,
    "OPC": 43,
    "CCI": 43,
    "TMT": 41,
    "KSH": 40,
    "SMC": 39,
    "KSA": 34,
    "SFI": 34,
    "SII": 33,
    "SFC": 32,
    "VID": 30,
    "SRF": 30,
    "SAV": 29,
    "SSC": 27,
    "DCM": 27,
    "DRH": 26,
    "BHN": 26,
    "SVC": 26,
    "PAN": 26,
    "ICF": 25,
    "CMV": 24,
    "ATG": 24,
    "FDC": 23,
    "HLG": 23,
    "PGC": 23,
    "TCO": 22,
    "BCG": 22,
    "HAI": 22,
    "TDW": 21,
    "CCL": 20,
    "SZL": 19,
    "NKG": 18,
    "HNG": 18,
    "SHA": 18,
    "LGL": 18,
    "SVT": 18,
    "IJC": 17,
    "CTD": 17,
    "BHS": 16,
    "HMC": 16,
    "LHG": 16,
    "TCR": 15,
    "KHP": 15,
    "HDG": 15,
    "HU1": 15,
    "BTT": 14,
    "PNC": 14,
    "SGT": 14,
    "SC5": 14,
    "SMA": 13,
    "PXT": 12,
    "BTP": 12,
    "KHA": 12,
    "PDR": 12,
    "DAH": 12,
    "GTA": 11,
    "PHR": 10,
    "TS4": 10,
    "VPH": 10,
    "QBS": 9,
    "VSI": 8,
    "VRC": 8,
    "ITD": 8,
    "ITA": 8,
    "HVX": 8,
    "NBB": 7,
    "LGC": 7,
    "TV1": 7,
    "CYC": 6,
    "ROS": 6,
    "PPI": 6,
    "TNT": 6,
    "VNS": 5,
    "NCT": 5,
    "ACL": 5,
    "SBA": 5,
    "TIC": 5,
    "VPK": 5,
    "TIX": 5,
    "HTV": 5,
    "COM": 5,
    "TCM": 5,
    "NT2": 4,
    "PDN": 4,
    "D2D": 4,
    "C32": 4,
    "SCD": 4,
    "GAS": 3,
    "CII": 3,
    "NTL": 3,
    "VAF": 3,
    "PTB": 3,
    "DPR": 3,
    "PNJ": 3,
    "SPM": 3,
    "VSH": 3,
    "LBM": 3,
    "TRC": 3,
    "APC": 3,
    "HID": 3,
    "SCR": 3,
    "ST8": 3,
    "FLC": 3,
    "DHA": 2,
    "VNE": 2,
    "ADS": 2,
    "HTI": 2,
    "TCT": 2,
    "FMC": 2,
    "VIC": 2,
    "PXS": 2,
    "VPS": 2,
    "REE": 2,
    "SVI": 2,
    "HRC": 2,
    "PGD": 2,
    "GMC": 2,
    "QCG": 2,
    "LDG": 2,
    "CLW": 2,
    "AGF": 1,
    "VNM": 1,
    "PC1": 1,
    "TNA": 1,
    "TDH": 1,
    "HPG": 1,
    "HAS": 1,
    "VTB": 1,
    "TYA": 1,
    "GSP": 1,
    "ASM": 1,
    "TAC": 1,
    "DTL": 1,
    "PXI": 1,
    "ABT": 1,
    "HHS": 1,
    "TMP": 1,
    "KDH": 1,
    "DXV": 1,
    "VIS": 1,
    "UIC": 1,
    "HSG": 1,
    "VJC": 1,
    "KDC": 1,
    "DGW": 1,
    "GDT": 1,
    "AGM": 1,
    "FCN": 1
}