{
    "So cong thuc khong dau tu": 1632,
    "IDI": 3319,
    "BFC": 3103,
    "TDC": 2346,
    "MWG": 2281,
    "HAX": 1282,
    "HAI": 1281,
    "IJC": 854,
    "ITD": 853,
    "HVG": 651,
    "TLH": 623,
    "SVC": 534,
    "PTB": 530,
    "PET": 460,
    "KSB": 444,
    "VNS": 443,
    "DLG": 430,
    "DCM": 387,
    "SMC": 384,
    "TMT": 366,
    "LDG": 349,
    "HSG": 308,
    "VPH": 293,
    "TCM": 287,
    "TRC": 266,
    "PTL": 249,
    "HAR": 248,
    "PGC": 242,
    "FIT": 233,
    "SZL": 223,
    "TRA": 210,
    "SFG": 189,
    "SBA": 178,
    "PNJ": 176,
    "PPI": 168,
    "MHC": 162,
    "CTD": 156,
    "DPR": 155,
    "MCP": 153,
    "HAG": 152,
    "PHR": 133,
    "PXS": 128,
    "TDH": 126,
    "DRC": 115,
    "QBS": 110,
    "DAG": 110,
    "VNM": 109,
    "TNT": 108,
    "VRC": 97,
    "CDO": 95,
    "SHI": 92,
    "GMC": 91,
    "SRC": 91,
    "HQC": 89,
    "CAV": 87,
    "LHG": 77,
    "DGW": 75,
    "NCT": 74,
    "VTO": 74,
    "RAL": 74,
    "ITA": 72,
    "DRH": 68,
    "CTI": 67,
    "KSA": 67,
    "HBC": 66,
    "TSC": 64,
    "MSN": 63,
    "VHG": 63,
    "HPG": 61,
    "TNA": 59,
    "KSH": 58,
    "GAS": 53,
    "HNG": 52,
    "BCG": 51,
    "PGD": 51,
    "BHS": 50,
    "HTI": 50,
    "NKG": 48,
    "DXG": 48,
    "AMD": 46,
    "VNE": 45,
    "D2D": 44,
    "APC": 43,
    "FMC": 40,
    "PDR": 40,
    "VNG": 39,
    "CSV": 39,
    "NBB": 39,
    "VIC": 38,
    "PAC": 36,
    "ASM": 35,
    "DHA": 33,
    "TMS": 33,
    "THG": 31,
    "CNG": 31,
    "HDG": 30,
    "GMD": 28,
    "TYA": 28,
    "VIS": 26,
    "FLC": 25,
    "LCG": 25,
    "CSM": 24,
    "PVT": 19,
    "NLG": 19,
    "CII": 18,
    "REE": 18,
    "SAM": 14,
    "NNC": 14,
    "VHC": 14,
    "SJS": 13,
    "KDH": 12,
    "NT2": 12,
    "QCG": 12,
    "DHM": 11,
    "BMC": 11,
    "PPC": 10,
    "ELC": 9,
    "LSS": 9,
    "PVD": 9,
    "C32": 9,
    "BMP": 9,
    "HHS": 9,
    "KDC": 9,
    "VSC": 9,
    "ITC": 9,
    "HT1": 8,
    "DPM": 8,
    "DQC": 8,
    "TLG": 8,
    "EVE": 7,
    "DCL": 6,
    "HDC": 6,
    "SKG": 6,
    "STG": 5,
    "KBC": 5,
    "FPT": 5,
    "VSH": 4,
    "FCN": 4,
    "LIX": 3,
    "DMC": 3,
    "IMP": 3,
    "DHG": 3,
    "GTN": 2,
    "DIG": 2,
    "NAF": 1,
    "TTF": 1,
    "SBT": 1
}