{
    "So cong thuc khong dau tu": 293,
    "BFC": 250,
    "IDI": 246,
    "FCM": 245,
    "HAX": 229,
    "TDC": 193,
    "SMC": 178,
    "PTB": 146,
    "HAI": 115,
    "MWG": 113,
    "CMG": 112,
    "IJC": 98,
    "PVD": 97,
    "TDH": 84,
    "ITD": 73,
    "VPH": 71,
    "KSS": 53,
    "HVG": 51,
    "PNC": 50,
    "TNT": 46,
    "VMD": 44,
    "VRC": 43,
    "LGL": 41,
    "FDC": 41,
    "GTT": 41,
    "DRH": 38,
    "HAR": 38,
    "SC5": 38,
    "CMV": 38,
    "TIE": 38,
    "TLH": 37,
    "ASP": 36,
    "UDC": 35,
    "PPI": 34,
    "CLG": 33,
    "HMC": 32,
    "SAV": 32,
    "CMX": 31,
    "LHG": 29,
    "PTL": 27,
    "HTL": 25,
    "ATA": 23,
    "VSI": 22,
    "ST8": 21,
    "L10": 20,
    "NVT": 19,
    "GIL": 19,
    "VNE": 18,
    "HAS": 18,
    "JVC": 18,
    "C47": 18,
    "CCL": 17,
    "CIG": 17,
    "SFC": 16,
    "ITA": 16,
    "LGC": 16,
    "CCI": 16,
    "DPR": 15,
    "VIP": 15,
    "LDG": 15,
    "TRA": 15,
    "LCG": 15,
    "SSC": 14,
    "DLG": 14,
    "CII": 14,
    "TCO": 13,
    "TMT": 12,
    "HLG": 12,
    "DTA": 11,
    "HAG": 11,
    "TCM": 11,
    "KHP": 11,
    "KAC": 11,
    "VLF": 11,
    "PTC": 10,
    "KHA": 10,
    "BGM": 10,
    "LBM": 10,
    "VNS": 10,
    "SII": 10,
    "SGT": 9,
    "PHR": 9,
    "ICF": 9,
    "VIC": 9,
    "NBB": 9,
    "CDC": 9,
    "PDN": 9,
    "DXG": 9,
    "SMA": 8,
    "KSB": 8,
    "SZL": 8,
    "SVC": 8,
    "MCP": 8,
    "LCM": 8,
    "VNH": 8,
    "HAP": 8,
    "D2D": 8,
    "PNJ": 8,
    "DRC": 8,
    "SRC": 7,
    "DTT": 7,
    "ANV": 7,
    "SHI": 7,
    "KDC": 7,
    "COM": 7,
    "BTT": 7,
    "PXT": 7,
    "AGF": 6,
    "PVT": 6,
    "SBA": 6,
    "CYC": 6,
    "FIT": 6,
    "MHC": 6,
    "HDG": 6,
    "VHC": 6,
    "POM": 6,
    "VID": 5,
    "ACC": 5,
    "HOT": 5,
    "PET": 5,
    "TRC": 5,
    "TMS": 5,
    "PXI": 5,
    "SVT": 5,
    "DCM": 5,
    "TNA": 4,
    "TNC": 4,
    "FLC": 4,
    "TS4": 4,
    "SFG": 4,
    "PGC": 4,
    "PXS": 4,
    "MCG": 4,
    "QBS": 4,
    "VHG": 4,
    "CTI": 4,
    "NSC": 4,
    "HHS": 4,
    "HSG": 4,
    "LM8": 4,
    "VOS": 4,
    "THG": 4,
    "LAF": 3,
    "PXL": 3,
    "EMC": 3,
    "SPM": 3,
    "PJT": 3,
    "VNG": 3,
    "HDC": 3,
    "BCE": 3,
    "DIC": 3,
    "NCT": 3,
    "REE": 3,
    "SHP": 3,
    "UIC": 3,
    "PIT": 3,
    "MDG": 3,
    "TDW": 3,
    "VNL": 3,
    "TIX": 3,
    "KSA": 3,
    "VSC": 3,
    "CLL": 2,
    "DIG": 2,
    "ITC": 2,
    "DTL": 2,
    "ACL": 2,
    "KMR": 2,
    "NKG": 2,
    "PPC": 2,
    "FCN": 2,
    "TCT": 2,
    "BHS": 2,
    "VNA": 2,
    "GAS": 2,
    "HU1": 2,
    "LSS": 2,
    "OPC": 2,
    "BCI": 2,
    "DAG": 2,
    "RDP": 2,
    "TCL": 2,
    "TV1": 2,
    "RAL": 2,
    "VTO": 2,
    "CSM": 2,
    "STG": 2,
    "TIC": 2,
    "KSH": 2,
    "BCG": 2,
    "STT": 2,
    "DHA": 2,
    "DXV": 2,
    "PDR": 2,
    "GTA": 1,
    "BTP": 1,
    "SBT": 1,
    "GMD": 1,
    "SJD": 1,
    "AAM": 1,
    "CDO": 1,
    "CAV": 1,
    "SAM": 1,
    "SCD": 1,
    "C32": 1,
    "NLG": 1,
    "CLW": 1,
    "VNM": 1,
    "TCR": 1,
    "VIS": 1,
    "CLC": 1,
    "VCF": 1,
    "HVX": 1,
    "SVI": 1,
    "GSP": 1,
    "HTI": 1,
    "VTB": 1,
    "HT1": 1,
    "SFI": 1,
    "PAN": 1,
    "AMD": 1,
    "DSN": 1,
    "DPM": 1,
    "PGD": 1,
    "CSV": 1,
    "CTD": 1
}