{
    "So cong thuc khong dau tu": 7061,
    "IDI": 855,
    "FCM": 706,
    "BFC": 693,
    "SMC": 568,
    "HAX": 558,
    "TDC": 418,
    "PTB": 417,
    "PVD": 341,
    "VPH": 336,
    "HAI": 306,
    "MWG": 285,
    "TDH": 251,
    "CMG": 231,
    "GTT": 230,
    "ITD": 226,
    "TCM": 196,
    "KSS": 178,
    "TIE": 178,
    "IJC": 174,
    "PNC": 170,
    "CDC": 130,
    "HMC": 125,
    "UDC": 124,
    "VMD": 112,
    "TCO": 106,
    "ASP": 103,
    "TLH": 102,
    "LGL": 100,
    "BTT": 98,
    "TNT": 96,
    "SSC": 91,
    "TMT": 91,
    "TRA": 86,
    "ATA": 80,
    "VNS": 79,
    "CLG": 76,
    "VIP": 75,
    "VHC": 72,
    "CMV": 70,
    "SC5": 69,
    "SVT": 68,
    "FDC": 66,
    "NVT": 66,
    "L10": 65,
    "DRH": 65,
    "HVG": 63,
    "CCI": 56,
    "PTL": 53,
    "CMX": 53,
    "SAV": 52,
    "JVC": 44,
    "LHG": 43,
    "LGC": 43,
    "SFC": 42,
    "HTL": 42,
    "ST8": 40,
    "LDG": 40,
    "VSI": 36,
    "GIL": 36,
    "VNE": 36,
    "PDR": 36,
    "FIT": 35,
    "DCM": 35,
    "SGT": 34,
    "PIT": 32,
    "CTD": 32,
    "POM": 31,
    "VIC": 30,
    "CIG": 29,
    "VLF": 28,
    "HAG": 28,
    "KDC": 28,
    "HAS": 27,
    "HAP": 27,
    "C47": 26,
    "PPI": 25,
    "GAS": 24,
    "DXG": 23,
    "DRC": 23,
    "ASM": 23,
    "NBB": 22,
    "HAR": 22,
    "VRC": 21,
    "DLG": 21,
    "KSB": 21,
    "D2D": 21,
    "PGC": 20,
    "KHP": 19,
    "PTC": 18,
    "NSC": 18,
    "SZL": 18,
    "KHA": 17,
    "CCL": 17,
    "SHI": 17,
    "TIX": 17,
    "HLG": 16,
    "PNJ": 16,
    "CYC": 16,
    "BCG": 16,
    "ITA": 15,
    "SVC": 15,
    "SII": 14,
    "VOS": 14,
    "VNM": 13,
    "LCG": 13,
    "PVT": 12,
    "ELC": 12,
    "ACL": 12,
    "DAG": 11,
    "PET": 11,
    "CII": 10,
    "HPG": 10,
    "PHR": 9,
    "HVX": 9,
    "DPR": 8,
    "LCM": 8,
    "MCP": 8,
    "PAN": 8,
    "TSC": 8,
    "HNG": 8,
    "STG": 8,
    "RDP": 7,
    "AMD": 7,
    "COM": 7,
    "BCE": 6,
    "VHG": 6,
    "HDC": 6,
    "SBA": 6,
    "SHP": 6,
    "NLG": 6,
    "TV1": 6,
    "BCI": 6,
    "VNH": 6,
    "PXL": 6,
    "MHC": 6,
    "CLW": 6,
    "TDW": 6,
    "CTI": 6,
    "VSC": 6,
    "QBS": 6,
    "AGF": 5,
    "SFG": 5,
    "PXI": 5,
    "ACC": 5,
    "VNL": 5,
    "MCG": 5,
    "FLC": 5,
    "TMS": 4,
    "DIC": 4,
    "PXT": 4,
    "SBT": 4,
    "TCL": 4,
    "BGM": 4,
    "HHS": 4,
    "VFG": 4,
    "PJT": 4,
    "CDO": 4,
    "ITC": 4,
    "LBM": 3,
    "VNG": 3,
    "SMA": 3,
    "RAL": 3,
    "TNA": 3,
    "VNA": 3,
    "OPC": 3,
    "HSG": 3,
    "SAM": 3,
    "HDG": 3,
    "DTA": 3,
    "THG": 3,
    "DPM": 3,
    "MDG": 3,
    "ICF": 2,
    "SRC": 2,
    "HOT": 2,
    "UIC": 2,
    "TNC": 2,
    "SRF": 2,
    "CMT": 2,
    "TIC": 2,
    "KAC": 2,
    "DHA": 2,
    "REE": 2,
    "VID": 2,
    "GSP": 2,
    "CLC": 2,
    "PDN": 2,
    "DXV": 2,
    "VTO": 2,
    "GTA": 2,
    "MSN": 2,
    "CAV": 2,
    "EMC": 2,
    "NKG": 1,
    "LAF": 1,
    "CSV": 1,
    "STT": 1,
    "DGW": 1,
    "PXS": 1,
    "SCD": 1,
    "SFI": 1,
    "DMC": 1,
    "TS4": 1,
    "BHS": 1,
    "TMP": 1,
    "TBC": 1,
    "BBC": 1,
    "HTV": 1,
    "GMC": 1,
    "CSM": 1,
    "DHG": 1,
    "NT2": 1,
    "DHM": 1,
    "SJS": 1,
    "QCG": 1,
    "AAM": 1,
    "VSH": 1,
    "FMC": 1,
    "AGM": 1,
    "HQC": 1,
    "FCN": 1,
    "HU1": 1
}