{
    "So cong thuc khong dau tu": 216,
    "HHS": 269,
    "TDM": 179,
    "HAR": 63,
    "IJC": 52,
    "SVT": 46,
    "AMD": 45,
    "HAI": 44,
    "BCM": 41,
    "GVR": 38,
    "NNC": 35,
    "DHA": 34,
    "ILB": 34,
    "FCM": 33,
    "DCM": 33,
    "SHI": 32,
    "D2D": 30,
    "VMD": 30,
    "DXV": 28,
    "TTB": 27,
    "SZC": 25,
    "CDC": 25,
    "PGC": 25,
    "QBS": 25,
    "CII": 24,
    "TTA": 24,
    "PHR": 23,
    "PTC": 22,
    "VID": 22,
    "TIP": 21,
    "TDH": 21,
    "HVN": 20,
    "YBM": 20,
    "PET": 17,
    "FIR": 17,
    "TDG": 17,
    "TRC": 16,
    "DPM": 16,
    "VIP": 16,
    "SKG": 15,
    "CTD": 15,
    "MHC": 15,
    "HQC": 15,
    "HID": 15,
    "TEG": 15,
    "HPG": 15,
    "NTL": 15,
    "ITC": 15,
    "PDN": 15,
    "TSC": 15,
    "SCS": 15,
    "TNH": 15,
    "ANV": 14,
    "SBV": 13,
    "DGW": 13,
    "AAM": 13,
    "VNE": 12,
    "HSL": 12,
    "PPC": 12,
    "LDG": 12,
    "TTF": 12,
    "DTA": 12,
    "VNL": 12,
    "DSN": 11,
    "TNI": 11,
    "DBT": 11,
    "CIG": 11,
    "MCG": 11,
    "HAX": 11,
    "RAL": 11,
    "TDP": 10,
    "DRH": 10,
    "TDC": 10,
    "ITD": 10,
    "PIT": 10,
    "CNG": 10,
    "CMG": 10,
    "DIG": 10,
    "ASP": 10,
    "UDC": 10,
    "DPR": 10,
    "VOS": 10,
    "IDI": 9,
    "FIT": 9,
    "AST": 9,
    "PXS": 9,
    "MWG": 9,
    "GAS": 9,
    "NAF": 9,
    "DC4": 9,
    "SZL": 8,
    "VRC": 8,
    "PSH": 8,
    "ASG": 8,
    "BWE": 8,
    "SRF": 8,
    "VRE": 8,
    "VJC": 8,
    "KSB": 8,
    "FLC": 8,
    "VAF": 8,
    "VNG": 8,
    "DMC": 7,
    "TLH": 7,
    "LCM": 7,
    "HDG": 7,
    "SMB": 7,
    "ELC": 7,
    "PTL": 7,
    "CTF": 7,
    "SMC": 7,
    "C32": 7,
    "APC": 6,
    "SCR": 6,
    "JVC": 6,
    "HTN": 6,
    "NKG": 6,
    "BFC": 6,
    "NT2": 6,
    "DGC": 6,
    "KDH": 6,
    "SVD": 5,
    "SFG": 5,
    "HVX": 5,
    "SAV": 5,
    "FDC": 5,
    "SFI": 5,
    "TMS": 5,
    "DVP": 5,
    "ADG": 5,
    "TVT": 5,
    "CKG": 5,
    "CCL": 5,
    "TCO": 5,
    "TMT": 5,
    "AAA": 5,
    "KHP": 5,
    "DHG": 5,
    "HMC": 5,
    "SJD": 5,
    "BCG": 4,
    "MSN": 4,
    "YEG": 4,
    "PNJ": 4,
    "CRC": 4,
    "FRT": 4,
    "SHA": 4,
    "DAH": 4,
    "DCL": 4,
    "LGL": 4,
    "HSG": 3,
    "AGM": 3,
    "VGC": 3,
    "TNA": 3,
    "VSC": 3,
    "NVL": 3,
    "HBC": 3,
    "PTB": 3,
    "HAG": 3,
    "DBD": 3,
    "POM": 3,
    "FMC": 3,
    "HVH": 3,
    "SGT": 3,
    "APH": 3,
    "VSH": 3,
    "GSP": 3,
    "VHM": 3,
    "HT1": 3,
    "SJS": 3,
    "GIL": 3,
    "VPH": 3,
    "FCN": 3,
    "GEX": 3,
    "SAM": 3,
    "BMP": 2,
    "EVE": 2,
    "TCD": 2,
    "HAP": 2,
    "DXG": 2,
    "NLG": 2,
    "VNM": 2,
    "CSM": 2,
    "GEG": 2,
    "DPG": 2,
    "FPT": 2,
    "TAC": 2,
    "KDC": 2,
    "ABS": 2,
    "KOS": 2,
    "DHM": 2,
    "MSH": 2,
    "CRE": 2,
    "HNG": 2,
    "GMD": 2,
    "PLX": 2,
    "KMR": 2,
    "HII": 2,
    "SMA": 2,
    "ROS": 2,
    "TNT": 2,
    "DLG": 2,
    "NHH": 2,
    "VCG": 2,
    "TGG": 2,
    "AAT": 2,
    "IBC": 2,
    "ASM": 2,
    "PC1": 2,
    "POW": 2,
    "VHC": 2,
    "PVT": 2,
    "ITA": 2,
    "TLD": 2,
    "LSS": 1,
    "SJF": 1,
    "EVG": 1,
    "DBC": 1,
    "PDR": 1,
    "DAG": 1,
    "LBM": 1,
    "SAB": 1,
    "QCG": 1,
    "VCA": 1,
    "DRC": 1,
    "VIC": 1,
    "SBT": 1,
    "PAN": 1,
    "LCG": 1,
    "TCM": 1,
    "PGD": 1,
    "PHC": 1,
    "THG": 1,
    "NBB": 1,
    "REE": 1,
    "HUB": 1,
    "KBC": 1,
    "ICT": 1,
    "PLP": 1,
    "AGG": 1,
    "LHG": 1,
    "OPC": 1,
    "TRA": 1,
    "HHP": 1
}