{
    "So cong thuc khong dau tu": 495,
    "EVE": 95,
    "APC": 63,
    "RAL": 62,
    "ITD": 60,
    "PET": 54,
    "MWG": 52,
    "NCT": 50,
    "TDC": 49,
    "LDG": 44,
    "HHS": 38,
    "TRA": 35,
    "SZL": 33,
    "LIX": 32,
    "DLG": 32,
    "BFC": 30,
    "FLC": 29,
    "BCG": 27,
    "GSP": 25,
    "DQC": 25,
    "LHG": 25,
    "SHI": 24,
    "VPG": 23,
    "DHA": 21,
    "FIT": 21,
    "NNC": 20,
    "CMG": 20,
    "HAX": 19,
    "CTD": 19,
    "DCM": 18,
    "CSV": 17,
    "KSB": 17,
    "VNM": 16,
    "HPG": 16,
    "IJC": 16,
    "FCM": 16,
    "GMD": 16,
    "TCM": 15,
    "SKG": 15,
    "MSN": 15,
    "HDG": 15,
    "NVT": 15,
    "DPM": 15,
    "HMC": 14,
    "HQC": 14,
    "FPT": 13,
    "DGW": 13,
    "HT1": 13,
    "ANV": 12,
    "PVT": 12,
    "HSG": 12,
    "PAN": 12,
    "DIG": 11,
    "VPH": 11,
    "DCL": 11,
    "PNJ": 10,
    "C32": 10,
    "CMX": 10,
    "BTP": 10,
    "HVG": 9,
    "VSC": 9,
    "VNG": 9,
    "HSL": 9,
    "DPR": 9,
    "BMP": 9,
    "TCL": 8,
    "NLG": 7,
    "VHC": 7,
    "DHG": 7,
    "JVC": 7,
    "IDI": 6,
    "HAR": 6,
    "KDC": 6,
    "GMC": 6,
    "SAM": 6,
    "KDH": 5,
    "AMD": 5,
    "THG": 5,
    "GIL": 5,
    "IMP": 5,
    "TDH": 5,
    "KBC": 5,
    "SAB": 4,
    "VNE": 4,
    "SCR": 4,
    "TLH": 4,
    "SJD": 4,
    "GAS": 4,
    "VSH": 4,
    "CII": 4,
    "VIC": 4,
    "CVT": 4,
    "ITA": 3,
    "TNA": 3,
    "PHR": 3,
    "REE": 3,
    "ASM": 3,
    "HAG": 3,
    "DAG": 3,
    "VJC": 3,
    "HNG": 3,
    "PTB": 3,
    "LSS": 3,
    "DRC": 3,
    "FRT": 3,
    "DAH": 2,
    "HBC": 2,
    "PPC": 2,
    "FCN": 2,
    "NVL": 2,
    "VRC": 2,
    "TRC": 2,
    "NKG": 2,
    "HAI": 2,
    "HRC": 2,
    "VPI": 2,
    "HAH": 2,
    "DXG": 2,
    "FIR": 1,
    "TTF": 1,
    "TIP": 1,
    "HDC": 1,
    "D2D": 1,
    "DPG": 1,
    "BWE": 1,
    "VRE": 1,
    "LGL": 1,
    "POW": 1,
    "SHP": 1,
    "PDR": 1,
    "ACL": 1,
    "VHG": 1,
    "SJS": 1,
    "CSM": 1,
    "EVG": 1,
    "PVD": 1,
    "PMG": 1,
    "NAF": 1,
    "LCG": 1
}