{
    "So cong thuc khong dau tu": 546,
    "HID": 60,
    "SSC": 56,
    "PVT": 39,
    "PTC": 37,
    "ASP": 34,
    "TCM": 33,
    "LGL": 31,
    "TIX": 30,
    "LBM": 28,
    "HTT": 27,
    "HTI": 27,
    "TEG": 26,
    "TDG": 25,
    "PET": 25,
    "HNG": 24,
    "VNL": 22,
    "DAH": 22,
    "SGT": 22,
    "DCM": 21,
    "SII": 21,
    "BFC": 21,
    "SVC": 20,
    "HAR": 20,
    "PPI": 19,
    "THI": 19,
    "CMV": 18,
    "IDI": 18,
    "MHC": 17,
    "PNC": 17,
    "CLL": 16,
    "TTE": 16,
    "TNC": 16,
    "VOS": 15,
    "VHG": 15,
    "SFC": 15,
    "ITD": 15,
    "DPR": 15,
    "VMD": 15,
    "TSC": 14,
    "ASM": 14,
    "SVT": 14,
    "CDC": 14,
    "FCN": 14,
    "TIE": 14,
    "RAL": 13,
    "PTL": 12,
    "VPI": 12,
    "KAC": 12,
    "SCD": 12,
    "ATG": 12,
    "VPH": 12,
    "HU1": 12,
    "FCM": 12,
    "DCL": 12,
    "DXV": 11,
    "SFI": 11,
    "VID": 11,
    "CLG": 10,
    "MCG": 10,
    "DIC": 10,
    "VFG": 10,
    "HMC": 10,
    "APC": 10,
    "ST8": 10,
    "AGM": 10,
    "STG": 10,
    "VNE": 10,
    "LDG": 9,
    "ICF": 9,
    "HUB": 9,
    "BCG": 9,
    "CMT": 9,
    "TDC": 9,
    "DSN": 9,
    "HAG": 9,
    "OPC": 9,
    "SRF": 9,
    "KSB": 9,
    "CCI": 9,
    "SCS": 8,
    "LCM": 8,
    "C47": 8,
    "SPM": 8,
    "TLG": 8,
    "LM8": 8,
    "BHN": 8,
    "QBS": 8,
    "TS4": 7,
    "COM": 7,
    "PME": 7,
    "CIG": 7,
    "FIT": 7,
    "ACC": 7,
    "SHI": 7,
    "PGC": 7,
    "HHS": 7,
    "PMG": 7,
    "CAV": 7,
    "BTT": 7,
    "TDW": 7,
    "HAX": 7,
    "SZL": 7,
    "BBC": 7,
    "BRC": 6,
    "SVI": 6,
    "TPC": 6,
    "EVG": 6,
    "YBM": 6,
    "IJC": 6,
    "D2D": 6,
    "SMC": 6,
    "VDP": 6,
    "BTP": 6,
    "RDP": 5,
    "VRC": 5,
    "DTA": 5,
    "KHP": 5,
    "PPC": 5,
    "TMP": 5,
    "IBC": 5,
    "HT1": 5,
    "TRC": 5,
    "TCR": 5,
    "CMG": 5,
    "SMB": 5,
    "AGF": 5,
    "VPS": 5,
    "TAC": 5,
    "TMS": 4,
    "LAF": 4,
    "DGW": 4,
    "TMT": 4,
    "ITA": 4,
    "PHC": 4,
    "UDC": 4,
    "GMD": 4,
    "SZC": 4,
    "VPK": 4,
    "TDH": 4,
    "PAN": 4,
    "VRE": 4,
    "DHA": 4,
    "TIP": 4,
    "CII": 3,
    "HVG": 3,
    "DRH": 3,
    "VIS": 3,
    "PDN": 3,
    "LHG": 3,
    "HPG": 3,
    "ANV": 3,
    "TNT": 3,
    "VNG": 3,
    "S4A": 3,
    "SBV": 3,
    "FDC": 3,
    "BWE": 3,
    "GMC": 3,
    "VTB": 3,
    "LGC": 3,
    "TDM": 3,
    "GTA": 3,
    "PHR": 3,
    "VSC": 3,
    "DXG": 3,
    "HLG": 3,
    "HTL": 3,
    "HDG": 3,
    "SAV": 3,
    "PDR": 3,
    "ADS": 3,
    "PIT": 3,
    "AAM": 3,
    "VSI": 3,
    "SFG": 2,
    "REE": 2,
    "KDC": 2,
    "HII": 2,
    "NCT": 2,
    "HAI": 2,
    "SBA": 2,
    "SHP": 2,
    "PXI": 2,
    "DAT": 2,
    "MDG": 2,
    "TNI": 2,
    "POM": 2,
    "CMX": 2,
    "DTL": 2,
    "PAC": 2,
    "TGG": 2,
    "DLG": 2,
    "HTN": 2,
    "GTN": 2,
    "NAV": 2,
    "VJC": 2,
    "CTF": 2,
    "DHM": 2,
    "KDH": 2,
    "NBB": 2,
    "DRL": 2,
    "VHC": 2,
    "TVT": 2,
    "HVX": 2,
    "FIR": 2,
    "CTI": 2,
    "HU3": 2,
    "HAH": 2,
    "ROS": 2,
    "TTF": 2,
    "HQC": 1,
    "CVT": 1,
    "ABT": 1,
    "DPG": 1,
    "DBD": 1,
    "PXT": 1,
    "EMC": 1,
    "VNS": 1,
    "JVC": 1,
    "MCP": 1,
    "CSV": 1,
    "TRA": 1,
    "EVE": 1,
    "SAB": 1,
    "PVD": 1,
    "GEX": 1,
    "GDT": 1,
    "VNM": 1,
    "SGN": 1,
    "HAP": 1,
    "FRT": 1,
    "DHG": 1,
    "HRC": 1,
    "CHP": 1,
    "TBC": 1,
    "ACL": 1,
    "PLP": 1,
    "DVP": 1,
    "KBC": 1,
    "GIL": 1,
    "SJD": 1,
    "C32": 1,
    "TCT": 1,
    "NLG": 1,
    "HTV": 1,
    "VAF": 1,
    "SC5": 1,
    "ITC": 1,
    "PJT": 1,
    "SMA": 1,
    "SGR": 1,
    "TNA": 1,
    "PC1": 1,
    "POW": 1,
    "VHM": 1,
    "CLW": 1,
    "STK": 1,
    "CEE": 1,
    "VIP": 1,
    "VCF": 1,
    "LEC": 1,
    "DIG": 1
}